gogo_scraper.py
gogo_scraper-1.0.1.dist-info/LICENSE
gogo_scraper-1.0.1.dist-info/METADATA
gogo_scraper-1.0.1.dist-info/WHEEL
gogo_scraper-1.0.1.dist-info/top_level.txt
gogo_scraper-1.0.1.dist-info/RECORD
