Metadata-Version: 2.1
Name: gogo-scraper
Version: 1.0.1
Summary: A simple web scraper to get information about anime from Gogoanime
Home-page: https://github.com/alanjoshua/gogo_scraper
Author: Alan Aneeth Jegaraj
Author-email: alanjoshua2002@gmail.com
License: MIT
Platform: UNKNOWN
